{
	"configurations" : 
	[
		{
			"directories" : 
			[
				{
					"build" : ".",
					"jsonFile" : "directory-.-Debug-d0094a50bb2071803777.json",
					"minimumCMakeVersion" : 
					{
						"string" : "3.26"
					},
					"projectIndex" : 0,
					"source" : ".",
					"targetIndexes" : 
					[
						0,
						1,
						2,
						3
					]
				}
			],
			"name" : "Debug",
			"projects" : 
			[
				{
					"directoryIndexes" : 
					[
						0
					],
					"name" : "Notes",
					"targetIndexes" : 
					[
						0,
						1,
						2,
						3
					]
				}
			],
			"targets" : 
			[
				{
					"directoryIndex" : 0,
					"id" : "copyConstructorDesctructor::@6890427a1f51a3e7e1df",
					"jsonFile" : "target-copyConstructorDesctructor-Debug-8a7b6757c1e0af0ec42a.json",
					"name" : "copyConstructorDesctructor",
					"projectIndex" : 0
				},
				{
					"directoryIndex" : 0,
					"id" : "file::@6890427a1f51a3e7e1df",
					"jsonFile" : "target-file-Debug-43c07460366fd9762e73.json",
					"name" : "file",
					"projectIndex" : 0
				},
				{
					"directoryIndex" : 0,
					"id" : "functions::@6890427a1f51a3e7e1df",
					"jsonFile" : "target-functions-Debug-26e54b520b61e4db8e83.json",
					"name" : "functions",
					"projectIndex" : 0
				},
				{
					"directoryIndex" : 0,
					"id" : "helper::@6890427a1f51a3e7e1df",
					"jsonFile" : "target-helper-Debug-aa57645501b9677202ee.json",
					"name" : "helper",
					"projectIndex" : 0
				}
			]
		}
	],
	"kind" : "codemodel",
	"paths" : 
	{
		"build" : "C:/Users/Benson/Documents/GitHub/CPP/Notes/cmake-build-debug",
		"source" : "C:/Users/Benson/Documents/GitHub/CPP/Notes"
	},
	"version" : 
	{
		"major" : 2,
		"minor" : 5
	}
}
